ZJUWebVPN.py
zjuwebvpn-0.2.1.dist-info/licenses/LICENSE
zjuwebvpn-0.2.1.dist-info/METADATA
zjuwebvpn-0.2.1.dist-info/WHEEL
zjuwebvpn-0.2.1.dist-info/top_level.txt
zjuwebvpn-0.2.1.dist-info/RECORD
