Metadata-Version: 2.4
Name: ZJUWebVPN
Version: 0.2.1
Summary: A Python wrapper for Zhejiang University WebVPN
Home-page: https://github.com/eWloYW8/ZJUWebVPN
Author: eWloYW8
Author-email: 3171132517@qq.com
License: WTFPL
Classifier: Programming Language :: Python :: 3
Classifier: License :: Public Domain
Classifier: Operating System :: OS Independent
Requires-Python: >=3.6
License-File: LICENSE
Requires-Dist: requests
Requires-Dist: pycryptodome
Requires-Dist: beautifulsoup4
Dynamic: author
Dynamic: author-email
Dynamic: classifier
Dynamic: description
Dynamic: description-content-type
Dynamic: home-page
Dynamic: license
Dynamic: license-file
Dynamic: requires-dist
Dynamic: requires-python
Dynamic: summary
